[
    { 
        "title": "Photo Portfolio",
        "slug": "hans",
        "details": "Clean and minimalist photography portfolio template written in bootstrap 5.",
        "lang": ["Portfolio", "PHP", "Bootstrap"],
        "link": "https://photo-mu.vercel.app/",
        "img": "./asset/photo.jpg",
        "text": "Visit Site",
        "feature" : "Portfolio Website",
        "theme": "#999999"
    },
    { 
        "title": "Peak Pilates",
        "slug": "peak-pilates",
        "details": "<i>Web designed by <a href='https://www.echowebsolutions.co.uk/websites/' target='_blank'>Echo</a>.</i> A woocommerce supported theme with several bespoke functionalies including a product comparison module and ACF powered blocks.",
        "lang": ["Wordpress", "PHP", "Bootstrap", "jQuery"],
        "feature" : "Woocommerce Website",
        "link": "https://peakpilates.co.uk/",
        "img": "./asset/pp.jpg",
        "text": "Visit Site",
        "theme": "#007aff"
    },
    { 
        "title": "The Medical Shop",
        "slug": "the-medical-shop",
        "details": "A modern bootstrap powered Opencart 3.x. theme created from scratch", 
        "lang": ["Ecommerce", "Twig", "Opencart"],
        "link": "https://medicalshop.ph",
        "img": "./asset/tms.jpg",
        "text": "Shop Online" ,
        "feature" : "Woocommerce Website",
        "theme": "rgb(244 190 30)"
    },
    { 
        "title": "Titanium Fireworks",
        "slug": "titanium-fireworks",
        "details": "<i>Web designed by <a href='https://www.echowebsolutions.co.uk/websites/' target='_blank'>Echo</a>.</i> Clean, minimalist wordpress theme with focus on high quality imagery featuring custom post types and bespoke forms.",
        "lang": ["Wordpress", "PHP", "Bootstrap", "jQuery"],
        "feature" : "Brochure Site",
        "link": "https://www.titaniumfireworks.com/",
        "img": "./asset/tf.jpg",
        "text": "Visit Site",
        "theme": "#2d2d2d"
    },
    { 
        "title": "GT Stoneworks",
        "slug": "gt-stoneworks",
        "details": "An android and iOS app created with React and compiled using Cordova. Backend is powered by a bespoke CMS written from scratch.", 
        "lang": ["App", "React", "Cordova", "PHP"],
        "link": "https://play.google.com/store/apps/details?id=org.stoneworksbeta.app",
        "img": "./asset/gt-1.jpg",
        "text": "Download",
        "feature" : "Mobile App",
        "theme": "#efddaf",
        "type": "mobile-app"
    },
    { 
        "title": "Stirling Maynard",
        "slug": "stirling-maynard",
        "details": "<i>Web designed by <a href='https://www.echowebsolutions.co.uk/websites/' target='_blank'>Echo</a>.</i> A bespoke wordpress theme created from scratch using ACF with support for custom post types.",
        "lang": ["Wordpress", "PHP", "Bootstrap", "jQuery"],
        "feature" : "Corporate Website",
        "link": "https://stirlingmaynard.com/",
        "img": "./asset/sm.jpg",
        "text": "Visit Site",
        "theme": "#b02712"
    },
    { 
        "title": "Scichart",
        "slug": "scichart",
        "details": "<i>One of my biggest projects from <a href='https://www.echowebsolutions.co.uk/websites/' target='_blank'>Echo</a>.</i> A fresh and modern theme that plays with dark and gradient colours. Features various API integrations, custom post types and forums.",
        "lang": ["Wordpress", "PHP", "Bootstrap", "jQuery"],
        "feature" : "Woocommerce Website",
        "link": "https://www.scichart.com/",
        "img": "./asset/sc.jpg",
        "text": "Visit Site",
        "theme": "#1a074b"
    },
    { 
        "title": "Marshal Papworth",
        "slug": "marshal-papworth",
        "details": "<i>Web designed by <a href='https://www.echowebsolutions.co.uk/websites/' target='_blank'>Echo</a>.</i> Flat, clean and bold colors with custom post type and map integration.",
        "lang": ["Wordpress", "PHP", "Bootstrap", "jQuery"],
        "feature" : "Membership Portal",
        "link": "https://www.marshalpapworth.com/",
        "img": "./asset/mp.jpg",
        "text": "Visit Site",
        "theme": "#8fc33e"
    }
]